jaraco/path.py
jaraco.path-3.7.1.dist-info/LICENSE
jaraco.path-3.7.1.dist-info/METADATA
jaraco.path-3.7.1.dist-info/WHEEL
jaraco.path-3.7.1.dist-info/top_level.txt
jaraco.path-3.7.1.dist-info/RECORD
